LICENSE
README.md
setup.py
stanag4586vsm/__init__.py
stanag4586vsm/controllable_entity.py
stanag4586vsm/entity_controller.py
stanag4586vsm/stanag_protocol.py
stanag4586vsm/stanag_server.py
stanag4586vsm.egg-info/PKG-INFO
stanag4586vsm.egg-info/SOURCES.txt
stanag4586vsm.egg-info/dependency_links.txt
stanag4586vsm.egg-info/top_level.txt