Metadata-Version: 2.1
Name: stanag4586vsm
Version: 0.0.15
Summary: Python Stanag 4586 VSM implementation
Home-page: https://github.com/faisalthaheem/python-stanag-4586-vsm
Author: Faisal Thaheem
License: GPLV3
Platform: UNKNOWN
Classifier: License :: OSI Approved :: GNU General Public License v3 (GPLv3)
Classifier: Programming Language :: Python :: 3
License-File: LICENSE
